Metadata-Version: 2.4
Name: pdf-manipulation-mcp-server-fastmcp
Version: 0.1.3
Summary: A study project: MCP server for direct PDF manipulation and editing
Project-URL: Homepage, https://github.com/fastmcp-me/pdf-manipulation-mcp-server#readme
Project-URL: Repository, https://github.com/fastmcp-me/pdf-manipulation-mcp-server.git
Project-URL: Issues, https://github.com/fastmcp-me/pdf-manipulation-mcp-server/issues
Author-email: André da Silva Medeiros <andr3medeiros@gmail.com>
License: MIT
License-File: LICENSE
Keywords: manipulation,mcp,pdf,server,study
Classifier: Development Status :: 3 - Alpha
Classifier: Intended Audience :: Developers
Classifier: License :: OSI Approved :: MIT License
Classifier: Programming Language :: Python :: 3
Classifier: Programming Language :: Python :: 3.10
Classifier: Programming Language :: Python :: 3.11
Classifier: Programming Language :: Python :: 3.12
Classifier: Topic :: Software Development :: Libraries :: Python Modules
Classifier: Topic :: Text Processing :: Markup
Requires-Python: >=3.10
Requires-Dist: mcp>=1.0.0
Requires-Dist: pymupdf>=1.23.0
Provides-Extra: dev
Requires-Dist: black>=23.0.0; extra == 'dev'
Requires-Dist: isort>=5.12.0; extra == 'dev'
Requires-Dist: pytest-asyncio>=0.21.0; extra == 'dev'
Requires-Dist: pytest>=7.0.0; extra == 'dev'
